
{
    "Layout": [{
        "title": "五星",
        "rows": [{
            "title": "五星直选",
            "parentname": "wxzh",
            "columns": [{
                "isrx": 0,
                "showname": "复式",
                "parentname": "wxzh",
                "shortname": "wxzhixfs",
                "realname": "[五星_复式]",
                "tips": "从个、十、百、千、万位各选一个号码组成一注。",
                "example": "投注方案：23456；开奖号码：23456，即中五星直选一等奖。",
                "help": "从万位、千位、百位、十位、个位中选择一个5位数号码组成一注，所选号码与开奖号码全部相同，且顺序一致，即为中奖。",
                "selectarea": {
                    "type": "digital",
                    "layout": [{
                        "title": "万位",
                        "balls": [0, 1, 2, 3, 4, 5, 6, 7, 8, 9],
                        "tools": true
                    }, {
                        "title": "千位",
                        "balls": [0, 1, 2, 3, 4, 5, 6, 7, 8, 9],
                        "tools": true
                    }, {
                        "title": "百位",
                        "balls": [0, 1, 2, 3, 4, 5, 6, 7, 8, 9],
                        "tools": true
                    }, {
                        "title": "十位",
                        "balls": [0, 1, 2, 3, 4, 5, 6, 7, 8, 9],
                        "tools": true
                    }, {
                        "title": "个位",
                        "balls": [0, 1, 2, 3, 4, 5, 6, 7, 8, 9],
                        "tools": true
                    }]
                }
            }, {
                "isrx": 0,
                "showname": "单式",
                "shortname": "wxzhixds",
                "parentname": "wxzh",
                "realname": "[五星_单式]",
                "tips": "手动输入号码，至少输入1个五位数号码组成一注。",
                "example": "投注方案：23456； 开奖号码：23456，即中五星直选一等奖",
                "help": "手动输入一个5位数号码组成一注，所选号码的万位、千位、百位、十位、个位与开奖号码相同，且顺序一致，即为中奖。",
                "selectarea": {
                    "type": "input"
                },
                "compressed": true
            }, {
                "isrx": 0,
                "showname": "组合",
                "shortname": "wxzhixzh",
                "parentname": "wxzh",
                "realname": "[五星_组合]",
                "tips": "从个、十、百、千、万位各选一个号码组成五注。",
                "example": "五星组合示例，如购买：4+5+6+7+8，该票共10元，由以下5注：45678(五星)、5678(四星)、678(三星)、78(二星)、8(一星)构成。开奖号码：45678，即可中五星、四星、三星、二星、一星的一等奖各1注。",
                "help": "从万位、千位、百位、十位、个位中至少各选一个号码组成1-5星的组合，共五注，所选号码的个位与开奖号码相同，则中1个5等奖；所选号码的个位、十位与开奖号码相同，则中1个5等奖以及1个4等奖，依此类推，最高可中5个奖。",
                "selectarea": {
                    "type": "digital",
                    "layout": [{
                        "title": "万位",
                        "balls": [0, 1, 2, 3, 4, 5, 6, 7, 8, 9],
                        "tools": true
                    }, {
                        "title": "千位",
                        "balls": [0, 1, 2, 3, 4, 5, 6, 7, 8, 9],
                        "tools": true
                    }, {
                        "title": "百位",
                        "balls": [0, 1, 2, 3, 4, 5, 6, 7, 8, 9],
                        "tools": true
                    }, {
                        "title": "十位",
                        "balls": [0, 1, 2, 3, 4, 5, 6, 7, 8, 9],
                        "tools": true
                    }, {
                        "title": "个位",
                        "balls": [0, 1, 2, 3, 4, 5, 6, 7, 8, 9],
                        "tools": true
                    }]
                }
            }]
        }, {
            "title": "五星组选",
            "parentname": "wuzux",
            "columns": [{
                "isrx": 0,
                "showname": "组选120",
                "shortname": "wxzux120",
                "parentname": "wuzux",
                "realname": "[五星_组选120]",
                "tips": "从0-9中选择5个号码组成一注。",
                "example": "投注方案：02568，开奖号码的五个数字只要包含0、2、5、6、8，即可中五星组选120一等奖。",
                "help": "从0-9中任意选择5个号码组成一注，所选号码与开奖号码的万位、千位、百位、十位、个位相同，顺序不限，即为中奖。",
                "selectarea": {
                    "type": "digital",
                    "layout": [{
                        "title": "选号",
                        "balls": [0, 1, 2, 3, 4, 5, 6, 7, 8, 9],
                        "tools": true
                    }]
                }
            }, {
                "isrx": 0,
                "showname": "组选60",
                "shortname": "wxzux60",
                "parentname": "wuzux",
                "realname": "[五星_组选60]",
                "tips": "从“二重号”选择一个号码，“单号”中选择三个号码组成一注。",
                "example": "投注方案：二重号：8，单号：0、2、5，只要开奖的5个数字包括 0、2、5、8、8，即可中五星组选60一等奖。",
                "help": "选择1个二重号码和3个单号号码组成一注，所选的单号号码与开奖号码相同，且所选二重号码在开奖号码中出现了2次，即为中奖。",
                "selectarea": {
                    "type": "digital",
                    "layout": [{
                        "title": "二重号",
                        "balls": [0, 1, 2, 3, 4, 5, 6, 7, 8, 9],
                        "tools": true
                    }, {
                        "title": "单　号",
                        "balls": [0, 1, 2, 3, 4, 5, 6, 7, 8, 9],
                        "tools": true
                    }]
                }
            }, {
                "isrx": 0,
                "showname": "组选30",
                "shortname": "wxzux30",
                "parentname": "wuzux",
                "realname": "[五星_组选30]",
                "tips": "从“二重号”选择两个号码，“单号”中选择一个号码组成一注。",
                "example": "投注方案：二重号：2、8，单号：0，只要开奖的5个数字包括 0、2、2、8、8，即可中五星组选30一等奖。",
                "help": "选择2个二重号和1个单号号码组成一注，所选的单号号码与开奖号码相同，且所选的2个二重号码分别在开奖号码中出现了2次，即为中奖。",
                "selectarea": {
                    "type": "digital",
                    "layout": [{
                        "title": "二重号",
                        "balls": [0, 1, 2, 3, 4, 5, 6, 7, 8, 9],
                        "tools": true
                    }, {
                        "title": "单　号",
                        "balls": [0, 1, 2, 3, 4, 5, 6, 7, 8, 9],
                        "tools": true
                    }]
                }
            }, {
                "isrx": 0,
                "showname": "组选20",
                "shortname": "wxzux20",
                "parentname": "wuzux",
                "realname": "[五星_组选20]",
                "tips": "从“三重号”选择一个号码，“单号”中选择两个号码组成一注。",
                "example": "投注方案：三重号：8，单号：0、2，只要开奖的5个数字包括 0、2、8、8、8，即可中五星组选20一等奖。",
                "help": "选择1个三重号码和2个单号号码组成一注，所选的单号号码与开奖号码相同，且所选三重号码在开奖号码中出现了3次，即为中奖。",
                "selectarea": {
                    "type": "digital",
                    "layout": [{
                        "title": "三重号",
                        "balls": [0, 1, 2, 3, 4, 5, 6, 7, 8, 9],
                        "tools": true
                    }, {
                        "title": "单　号",
                        "balls": [0, 1, 2, 3, 4, 5, 6, 7, 8, 9],
                        "tools": true
                    }]
                }
            }, {
                "isrx": 0,
                "showname": "组选10",
                "shortname": "wxzux10",
                "parentname": "wuzux",
                "realname": "[五星_组选10]",
                "tips": "从“三重号”选择一个号码，“二重号”中选择一个号码组成一注。",
                "example": "投注方案：三重号：8，二重号：2，只要开奖的5个数字包括 2、2、8、8、8，即可中五星组选10一等奖。",
                "help": "选择1个三重号码和1个二重号码，所选三重号码在开奖号码中出现3次，并且所选二重号码在开奖号码中出现了2次，即为中奖。",
                "selectarea": {
                    "type": "digital",
                    "layout": [{
                        "title": "三重号",
                        "balls": [0, 1, 2, 3, 4, 5, 6, 7, 8, 9],
                        "tools": true
                    }, {
                        "title": "二重号",
                        "balls": [0, 1, 2, 3, 4, 5, 6, 7, 8, 9],
                        "tools": true
                    }]
                }
            }, {
                "isrx": 0,
                "showname": "组选5",
                "shortname": "wxzux5",
                "parentname": "wuzux",
                "realname": "[五星_组选5]",
                "tips": "从“四重号”选择一个号码，“单号”中选择一个号码组成一注。",
                "example": "投注方案：四重号：8，单号：2，只要开奖的5个数字包括 2、8、8、8、8，即可中五星组选5一等奖。",
                "help": "选择1个四重号码和1个单号号码组成一注，所选的单号号码与开奖号码相同，且所选四重号码在开奖号码中出现了4次，即为中奖。",
                "selectarea": {
                    "type": "digital",
                    "layout": [{
                        "title": "四重号",
                        "balls": [0, 1, 2, 3, 4, 5, 6, 7, 8, 9],
                        "tools": true
                    }, {
                        "title": "单　号",
                        "balls": [0, 1, 2, 3, 4, 5, 6, 7, 8, 9],
                        "tools": true
                    }]
                }
            }]
        }, {
            "title": "五星其它",
            "parentname": "wuqt",
            "columns": [{
                "isrx": 0,
                "showname": "总和大小单双",
                "shortname": "wxdxds",
                "parentname": "wuqt",
                "realname": "[五星_总和大小单双]",
                "tips": "从总和大、小、单、双中任意选择1个号码形态组成一注。",
                "example": "投注方案：总和大。开奖号码：16568，开奖号码的总和26，即中总和大。",
                "help": "从总和大、小、单、双中任意选择1个号码形态组成一注，只要所选形态与开奖号码的5位数号码总和(大于等于23:总和大、小于等于22：总和小、单数：总和单、双数：总和双)形态相同，即为中奖。",
                "selectarea": {
                    "type": "digital",
                    "layout": [{
                        "title": "五星总和大小单双",
                        "balls": ["总和大", "总和小", "总和单", "总和双"],
                        "tools": false,
                        "showBallsAsValue": true
                    }]
                }
            }]
        }]
    }, {
        "title": "后四",
        "rows": [{
            "title": "后四直选",
            "parentname": "sixzhix",
            "columns": [{
                "isrx": 0,
                "showname": "复式",
                "shortname": "sixzhixfsh",
                "parentname": "sixzhix",
                "realname": "[后四星_复式]",
                "tips": "从千位、百位、十位、个位中选择一个4位数号码组成一注",
                "example": "投注方案：3456；开奖号码：*3456，即中四星直选。",
                "help": "从千位、百位、十位、个位中选择一个4位数号码组成一注，所选号码与开奖号码相同，且顺序一致，即为中奖。",
                "selectarea": {
                    "type": "digital",
                    "layout": [{
                        "title": "千位",
                        "balls": [0, 1, 2, 3, 4, 5, 6, 7, 8, 9],
                        "tools": true
                    }, {
                        "title": "百位",
                        "balls": [0, 1, 2, 3, 4, 5, 6, 7, 8, 9],
                        "tools": true
                    }, {
                        "title": "十位",
                        "balls": [0, 1, 2, 3, 4, 5, 6, 7, 8, 9],
                        "tools": true
                    }, {
                        "title": "个位",
                        "balls": [0, 1, 2, 3, 4, 5, 6, 7, 8, 9],
                        "tools": true
                    }]
                }
            }, {
                "isrx": 0,
                "showname": "单式",
                "shortname": "sixzhixdsh",
                "parentname": "sixzhix",
                "realname": "[后四星_单式]",
                "tips": "手动输入号码，至少输入1个四位数号码组成一注。",
                "example": "投注方案：3456； 开奖号码：3456，即中四星直选一等奖。",
                "help": "手动输入一个4位数号码组成一注，所选号码的千位、百位、十位、个位与开奖号码相同，且顺序一致，即为中奖。",
                "selectarea": {
                    "type": "input"
                },
                "compressed": true
            }, {
                "isrx": 0,
                "showname": "组合",
                "shortname": "sixzhixzhh",
                "parentname": "sixzhix",
                "realname": "[后四星_组合]",
                "tips": "在千位，百位，十位，个位任意位置上任意选择1个或1个以上号码。",
                "example": "5+6+7+8，开奖号码：*5678，即可中四星、三星、二星、一星各1注。",
                "help": "从千位、百位、十位、个位中至少各选一个号码组成1-4星的组合，共四注，所选号码的个位与开奖号码相同，则中1个4等奖；所选号码的个位、十位与开奖号码相同，则中1个4等奖以及1个3等奖，依此类推，最高可中4个奖。",
                "selectarea": {
                    "type": "digital",
                    "layout": [{
                        "title": "千位",
                        "balls": [0, 1, 2, 3, 4, 5, 6, 7, 8, 9],
                        "tools": true
                    }, {
                        "title": "百位",
                        "balls": [0, 1, 2, 3, 4, 5, 6, 7, 8, 9],
                        "tools": true
                    }, {
                        "title": "十位",
                        "balls": [0, 1, 2, 3, 4, 5, 6, 7, 8, 9],
                        "tools": true
                    }, {
                        "title": "个位",
                        "balls": [0, 1, 2, 3, 4, 5, 6, 7, 8, 9],
                        "tools": true
                    }]
                }
            }]
        }, {
            "title": "后四组选",
            "parentname": "sixzux",
            "columns": [{
                "isrx": 0,
                "showname": "组选24",
                "shortname": "sixzux24h",
                "parentname": "sixzux",
                "realname": "[后四星_组选24]",
                "tips": "从0-9中选择4个号码组成一注。",
                "example": "投注方案：0568，开奖号码的四个数字只要包含0、5、6、8，即可中四星组选24一等奖。",
                "help": "从0-9中任意选择4个号码组成一注，所选号码与开奖号码的千位、百位、十位、个位相同，且顺序不限，即为中奖。",
                "selectarea": {
                    "type": "digital",
                    "layout": [{
                        "title": "选号",
                        "balls": [0, 1, 2, 3, 4, 5, 6, 7, 8, 9],
                        "tools": true
                    }]
                }
            }, {
                "isrx": 0,
                "showname": "组选12",
                "shortname": "sixzux12h",
                "parentname": "sixzux",
                "realname": "[后四星_组选12]",
                "tips": "从“二重号”选择一个号码，“单号”中选择两个号码组成一注。",
                "example": "投注方案：二重号：8，单号：0、6，只要开奖的四个数字包括 0、6、8、8，即可中四星组选12一等奖。",
                "help": "选择1个二重号码和2个单号号码组成一注，所选单号号码与开奖号码相同，且所选二重号码在开奖号码中出现了2次，即为中奖。选择1个二重号码和2个单号号码组成一注，所选单号号码与开奖号码相同，且所选二重号码在开奖号码中出现了2次，即为中奖。",
                "selectarea": {
                    "type": "digital",
                    "layout": [{
                        "title": "二重号",
                        "balls": [0, 1, 2, 3, 4, 5, 6, 7, 8, 9],
                        "tools": true
                    }, {
                        "title": "单　号",
                        "balls": [0, 1, 2, 3, 4, 5, 6, 7, 8, 9],
                        "tools": true
                    }]
                }
            }, {
                "isrx": 0,
                "showname": "组选6",
                "shortname": "sixzux6h",
                "parentname": "sixzux",
                "realname": "[后四星_组选6]",
                "tips": "从“二重号”选择两个号码组成一注。",
                "example": "投注方案：二重号：6、8，只要开奖的四个数字从小到大排列为 6、6、8、8，即可中四星组选6。",
                "help": "选择2个二重号码组成一注，所选的2个二重号码在开奖号码中分别出现了2次，即为中奖。",
                "selectarea": {
                    "type": "digital",
                    "layout": [{
                        "title": "二重号",
                        "balls": [0, 1, 2, 3, 4, 5, 6, 7, 8, 9],
                        "tools": true
                    }]
                }
            }, {
                "isrx": 0,
                "showname": "组选4",
                "shortname": "sixzux4h",
                "parentname": "sixzux",
                "realname": "[后四星_组选4]",
                "tips": "从“三重号”选择一个号码，“单号”中选择两个号码组成一注。",
                "example": "投注方案：三重号：8，单号：2，只要开奖的四个数字从小到大排列为 2、8、8、8，即可中四星组选4。",
                "help": "选择1个三重号码和1个单号号码组成一注，所选单号号码与开奖号码相同，且所选三重号码在开奖号码中出现了3次，即为中奖。",
                "selectarea": {
                    "type": "digital",
                    "layout": [{
                        "title": "三重号",
                        "balls": [0, 1, 2, 3, 4, 5, 6, 7, 8, 9],
                        "tools": true
                    }, {
                        "title": "单　号",
                        "balls": [0, 1, 2, 3, 4, 5, 6, 7, 8, 9],
                        "tools": true
                    }]
                }
            }]
        }]
    }, {
        "title": "前四",
        "rows": [{
            "title": "前四直选",
            "parentname": "qszx",
            "columns": [{
                "isrx": 0,
                "showname": "复式",
                "shortname": "sixzhixfsq",
                "parentname": "qszx",
                "realname": "[前四星_复式]",
                "tips": "从万位、千位、百位、十位中选择一个4位数号码组成一注",
                "example": "投注方案：3456；开奖号码：3456*，即中四星直选。",
                "help": "从万位、千位、百位、十位中选择一个4位数号码组成一注，所选号码与开奖号码相同，且顺序一致，即为中奖。",
                "selectarea": {
                    "type": "digital",
                    "layout": [{
                        "title": "万位",
                        "balls": [0, 1, 2, 3, 4, 5, 6, 7, 8, 9],
                        "tools": true
                    }, {
                        "title": "千位",
                        "balls": [0, 1, 2, 3, 4, 5, 6, 7, 8, 9],
                        "tools": true
                    }, {
                        "title": "百位",
                        "balls": [0, 1, 2, 3, 4, 5, 6, 7, 8, 9],
                        "tools": true
                    }, {
                        "title": "十位",
                        "balls": [0, 1, 2, 3, 4, 5, 6, 7, 8, 9],
                        "tools": true
                    }]
                }
            }, {
                "isrx": 0,
                "showname": "单式",
                "shortname": "sixzhixdsq",
                "parentname": "qszx",
                "realname": "[前四星_单式]",
                "tips": "手动输入号码，至少输入1个四位数号码组成一注。",
                "example": "投注方案：3456； 开奖号码：3456，即中四星直选一等奖",
                "help": "手动输入一个4位数号码组成一注，所选号码的千位、百位、十位、个位与开奖号码相同，且顺序一致，即为中奖。",
                "selectarea": {
                    "type": "input"
                },
                "compressed": true
            }, {
                "isrx": 0,
                "showname": "组合",
                "shortname": "sixzhixzhq",
                "parentname": "qszx",
                "realname": "[前四星_组合]",
                "tips": "在万位、千位、百位、十位任意位置上任意选择1个或1个以上号码。",
                "example": "投注方案：5+6+7+8，开奖号码： 5678*，即可中四星、三星、二星、一星各1注。",
                "help": "从万位、千位、百位、十位中至少各选一个号码组成1-4星的组合，共四注，所选号码的个位与开奖号码相同，则中1个4等奖；所选号码的个位、十位与开奖号码相同，则中1个4等奖以及1个3等奖，依此类推，最高可中4个奖。",
                "selectarea": {
                    "type": "digital",
                    "layout": [{
                        "title": "万位",
                        "balls": [0, 1, 2, 3, 4, 5, 6, 7, 8, 9],
                        "tools": true
                    }, {
                        "title": "千位",
                        "balls": [0, 1, 2, 3, 4, 5, 6, 7, 8, 9],
                        "tools": true
                    }, {
                        "title": "百位",
                        "balls": [0, 1, 2, 3, 4, 5, 6, 7, 8, 9],
                        "tools": true
                    }, {
                        "title": "十位",
                        "balls": [0, 1, 2, 3, 4, 5, 6, 7, 8, 9],
                        "tools": true
                    }]
                }
            }]
        }, {
            "title": "前四组选",
            "parentname": "qszux",
            "columns": [{
                "isrx": 0,
                "showname": "组选24",
                "parentname": "qszux",
                "shortname": "sixzux24q",
                "realname": "[前四星_组选24]",
                "tips": "从0-9中选择4个号码组成一注。",
                "example": "投注方案：0568，开奖号码的四个数字只要包含0、5、6、8，即可中四星组选24一等奖。",
                "help": "从0-9中任意选择4个号码组成一注，所选号码与开奖号码的万位、千位、百位、十位相同，且顺序不限，即为中奖。",
                "selectarea": {
                    "type": "digital",
                    "layout": [{
                        "title": "选号",
                        "balls": [0, 1, 2, 3, 4, 5, 6, 7, 8, 9],
                        "tools": true
                    }]
                }
            }, {
                "isrx": 0,
                "showname": "组选12",
                "shortname": "sixzux12q",
                "parentname": "qszux",
                "realname": "[前四星_组选12]",
                "tips": "从“二重号”选择一个号码，“单号”中选择两个号码组成一注。",
                "example": "投注方案：二重号：8，单号：0、6，只要开奖的四个数字包括 0、6、8、8，即可中四星组选12一等奖。",
                "help": "选择1个二重号码和2个单号号码组成一注，所选单号号码与开奖号码相同，且所选二重号码在开奖号码中出现了2次，即为中奖。",
                "selectarea": {
                    "type": "digital",
                    "layout": [{
                        "title": "二重号",
                        "balls": [0, 1, 2, 3, 4, 5, 6, 7, 8, 9],
                        "tools": true
                    }, {
                        "title": "单　号",
                        "balls": [0, 1, 2, 3, 4, 5, 6, 7, 8, 9],
                        "tools": true
                    }]
                }
            }, {
                "isrx": 0,
                "showname": "组选6",
                "shortname": "sixzux6q",
                "parentname": "qszux",
                "realname": "[前四星_组选6]",
                "tips": "从“二重号”选择两个号码组成一注。",
                "example": "投注方案：二重号：6、8，只要开奖的四个数字从小到大排列为 6、6、8、8，即可中四星组选6。",
                "help": "选择2个二重号码组成一注，所选的2个二重号码在开奖号码中分别出现了2次，即为中奖。",
                "selectarea": {
                    "type": "digital",
                    "layout": [{
                        "title": "二重号",
                        "balls": [0, 1, 2, 3, 4, 5, 6, 7, 8, 9],
                        "tools": true
                    }]
                }
            }, {
                "isrx": 0,
                "showname": "组选4",
                "shortname": "sixzux4q",
                "realname": "[前四星_组选4]",
                "parentname": "qszux",
                "tips": "从“三重号”选择一个号码，“单号”中选择两个号码组成一注。",
                "example": "投注方案：三重号：8，单号：2，只要开奖的四个数字从小到大排列为 2、8、8、8，即可中四星组选4。",
                "help": "选择1个三重号码和1个单号号码组成一注，所选单号号码与开奖号码相同，且所选三重号码在开奖号码中出现了3次，即为中奖。",
                "selectarea": {
                    "type": "digital",
                    "layout": [{
                        "title": "三重号",
                        "balls": [0, 1, 2, 3, 4, 5, 6, 7, 8, 9],
                        "tools": true
                    }, {
                        "title": "单　号",
                        "balls": [0, 1, 2, 3, 4, 5, 6, 7, 8, 9],
                        "tools": true
                    }]
                }
            }]
        }]
    }, {
        "title": "后三",
        "rows": [{
            "title": "后三直选",
            "parentname": "hszx",
            "defaultmethod": "sxzhixfsh",
            "columns": [{
                "isrx": 0,
                "showname": "复式",
                "shortname": "sxzhixfsh",
                "parentname": "hszx",
                "realname": "[后三码_复式]",
                "tips": "从个、十、百位各选一个号码组成一注。",
                "example": "投注方案：345；开奖号码：345；即中后三直选一等奖",
                "help": "从百位、十位、个位中选择一个3位数号码组成一注，所选号码与开奖号码后3位相同，且顺序一致，即为中奖。",
                "selectarea": {
                    "type": "digital",
                    "layout": [{
                        "title": "百位",
                        "balls": [0, 1, 2, 3, 4, 5, 6, 7, 8, 9],
                        "tools": true
                    }, {
                        "title": "十位",
                        "balls": [0, 1, 2, 3, 4, 5, 6, 7, 8, 9],
                        "tools": true
                    }, {
                        "title": "个位",
                        "balls": [0, 1, 2, 3, 4, 5, 6, 7, 8, 9],
                        "tools": true
                    }]
                }
            }, {
                "isrx": 0,
                "showname": "单式",
                "shortname": "sxzhixdsh",
                "parentname": "hszx",
                "realname": "[后三码_单式]",
                "tips": "手动输入号码，至少输入1个三位数号码组成一注。",
                "example": "投注方案：345； 开奖号码：345，即中后三直选一等奖。",
                "help": "手动输入一个3位数号码组成一注，所选号码的百位、十位、个位与开奖号码相同，且顺序一致，即为中奖。",
                "selectarea": {
                    "type": "input"
                }
            }, {
                "isrx": 0,
                "showname": "直选和值",
                "shortname": "sxzhixhzh",
                "parentname": "hszx",
                "realname": "[后三码_和值]",
                "tips": "从0-27中任意选择1个或1个以上号码",
                "example": "投注方案：和值1；开奖号码后三位：001,010,100,即中后三直选一等奖。",
                "help": "所选数值等于开奖号码的百位、十位、个位三个数字相加之和，即为中奖。",
                "selectarea": {
                    "type": "digital",
                    "layout": [{
                        "balls": [0, 1, 2, 3, 4, 5, 6, 7, 8, 9, 10, 11, 12, 13, 14, 15, 16, 17, 18, 19, 20, 21, 22, 23, 24, 25, 26, 27],
                        "tools": false,
                        "cls": "hz"
                    }]
                }
            }]
        }, {
            "title": "后三组选",
            "parentname": "hszux",
            "columns": [{
                "isrx": 0,
                "showname": "组三",
                "shortname": "sxzuxzsh",
                "parentname": "hszux",
                "realname": "[后三码_组三]",
                "tips": "从0-9中任意选择2个或2个以上号码。",
                "example": "投注方案：5,8,8；开奖号码后三位：1个5，2个8 (顺序不限)，即中后三组选三一等奖。",
                "help": "从0-9中选择2个数字组成两注，所选号码与开奖号码的百位、十位、个位相同，且顺序不限，即为中奖。",
                "selectarea": {
                    "type": "digital",
                    "layout": [{
                        "title": "组三",
                        "balls": [0, 1, 2, 3, 4, 5, 6, 7, 8, 9],
                        "tools": true
                    }]
                }
            }, {
                "isrx": 0,
                "showname": "组六",
                "shortname": "sxzuxzlh",
                "parentname": "hszux",
                "realname": "[后三码_组六]",
                "tips": "从0-9中任意选择3个或3个以上号码。",
                "example": "投注方案：2,5,8；开奖号码后三位：1个2、1个5、1个8 (顺序不限)，即中后三组选六一等奖。",
                "help": "从0-9中任意选择3个号码组成一注，所选号码与开奖号码的百位、十位、个位相同，顺序不限，即为中奖。",
                "selectarea": {
                    "type": "digital",
                    "layout": [{
                        "title": "组六",
                        "balls": [0, 1, 2, 3, 4, 5, 6, 7, 8, 9],
                        "tools": true
                    }]
                }
            }, {
                "isrx": 0,
                "showname": "混合组选",
                "parentname": "hszux",
                "shortname": "sxhhzxh",
                "realname": "[后三码_混合组选]",
                "tips": "手动输入号码，至少输入1个三位数号码。",
                "example": "投注方案：分別投注(0,0,1),以及(1,2,3)，开奖号码后三位包括：(1)0,0,1，顺序不限，即中得组三一等奖；或者(2)1,2,3，顺序不限，即中得组六一等奖。",
                "help": "手动输入购买号码，3个数字为一注，开奖号码的百位、十位、个位符合后三组三或组六均为中奖。",
                "selectarea": {
                    "type": "input"
                }
            }, {
                "isrx": 0,
                "showname": "组选和值",
                "shortname": "sxzuxhzh",
                "parentname": "hszux",
                "realname": "[后三码_组选和值]",
                "tips": "从1-26中选择1个号码。",
                "example" : "所选数值等于开奖号码百位、十位、个位三个数字相加之和（豹子除外），即为中奖。",
                "help": "投注方案：和值3；开奖号码后三位：(1)开出003号码，顺序不限，即中后三组三；(2)开出012号码，顺序不限，即中后三组六。",
                "selectarea": {
                    "type": "digital",
                    "layout": [{
                        "balls": [1, 2, 3, 4, 5, 6, 7, 8, 9, 10, 11, 12, 13, 14, 15, 16, 17, 18, 19, 20, 21, 22, 23, 24, 25, 26],
                        "tools": false,
                        "cls": "hz"
                    }]
                }
            }]
        }]
    }, {
        "title": "中三",
        "rows": [{
            "title": "中三直选",
            "parentname": "zszx",
            "columns": [{
                "isrx": 0,
                "showname": "复式",
                "shortname": "sxzhixfsz",
                "parentname": "zszx",
                "realname": "[中三码_复式]",
                "tips": "从千、百、十位各选一个号码组成一注。",
                "example": "投注方案：456； 开奖号码：3456，即中中三直选一等奖。",
                "help": "从千位、百位、十位中选择一个3位数号码组成一注，所选号码与开奖号码的中间3位相同，且顺序一致，即为中奖。",
                "selectarea": {
                    "type": "digital",
                    "layout": [{
                        "title": "千位",
                        "balls": [0, 1, 2, 3, 4, 5, 6, 7, 8, 9],
                        "tools": true
                    }, {
                        "title": "百位",
                        "balls": [0, 1, 2, 3, 4, 5, 6, 7, 8, 9],
                        "tools": true
                    }, {
                        "title": "十位",
                        "balls": [0, 1, 2, 3, 4, 5, 6, 7, 8, 9],
                        "tools": true
                    }]
                }
            }, {
                "isrx": 0,
                "showname": "单式",
                "parentname": "zszx",
                "shortname": "sxzhixdsz",
                "realname": "[中三码_单式]",
                "tips": "手动输入号码，至少输入1个三位数号码组成一注。",
                "example": "投注方案：345； 开奖号码：2345，即中中三直选一等奖。",
                "help": "手动输入一个3位数号码组成一注，所选号码的千位、百位、十位与开奖号码相同，且顺序一致，即为中奖。",
                "selectarea": {
                    "type": "input"
                }
            }, {
                "isrx": 0,
                "showname": "直选和值",
                "parentname": "zszx",
                "shortname": "sxzhixhzz",
                "realname": "[中三码_和值]",
                "tips": "从0-27中任意选择1个或1个以上号码",
                "example": "投注方案：和值1；开奖号码中间三位：01001,00010,00100,即中中三直选一等奖",
                "help": "所选数值等于开奖号码的千位、百位、十位三个数字相加之和，即为中奖。",
                "selectarea": {
                    "type": "digital",
                    "layout": [{
                        "balls": [0, 1, 2, 3, 4, 5, 6, 7, 8, 9, 10, 11, 12, 13, 14, 15, 16, 17, 18, 19, 20, 21, 22, 23, 24, 25, 26, 27],
                        "tools": false,
                        "cls": "hz"
                    }]
                }
            }]
        }, {
            "title": "中三组选",
            "parentname": "zszux",
            "columns": [{
                "isrx": 0,
                "showname": "组三",
                "shortname": "sxzuxzsz",
                "parentname": "zszux",
                "realname": "[中三码_组三]",
                "tips": "从0-9中任意选择2个或2个以上号码。",
                "example": "投注方案：5,8,8；开奖号码中间三位：1个5，2个8 (顺序不限)，即中中三组选三一等奖。",
                "help": "从0-9中选择2个数字组成两注，所选号码与开奖号码的千位、百位、十位相同，且顺序不限，即为中奖。",
                "selectarea": {
                    "type": "digital",
                    "layout": [{
                        "title": "组三",
                        "balls": [0, 1, 2, 3, 4, 5, 6, 7, 8, 9],
                        "tools": true
                    }]
                }
            }, {
                "isrx": 0,
                "showname": "组六",
                "shortname": "sxzuxzlz",
                "parentname": "zszux",
                "realname": "[中三码_组六]",
                "tips": "从0-9中任意选择3个或3个以上号码。",
                "example": "投注方案：2,5,8；开奖号码中间三位：1个2、1个5、1个8 (顺序不限)，即中中三组选六一等奖。",
                "help": "从0-9中任意选择3个号码组成一注，所选号码与开奖号码的千位、百位、十位相同，顺序不限，即为中奖。",
                "selectarea": {
                    "type": "digital",
                    "layout": [{
                        "title": "组六",
                        "balls": [0, 1, 2, 3, 4, 5, 6, 7, 8, 9],
                        "tools": true
                    }]
                }
            }, {
                "isrx": 0,
                "showname": "混合组选",
                "shortname": "sxhhzxz",
                "parentname": "zszux",
                "realname": "[中三码_混合组选]",
                "tips": "手动输入号码，至少输入1个三位数号码。",
                "example": "投注方案：分別投注(0,0,1),以及(1,2,3)，开奖号码中间三位包括：(1)0,0,1，顺序不限，即中得组三一等奖；或者(2)1,2,3，顺序不限，即中得组六一等奖。",
                "help": "手动输入购买号码，3个数字为一注，开奖号码的千位、百位、十位符合中三组三或组六均为中奖。",
                "selectarea": {
                    "type": "input"
                }
            },{
                "isrx": 0,
                "showname": "组选和值",
                "shortname": "sxzuxhzz",
                "parentname": "zszux",
                "realname": "[中三码_组选和值]",
                "tips": "从1-26中选择1个号码。",
                "example" : "所选数值等于开奖号码千位、百位、个位三个数字相加之和（豹子除外），即为中奖。",
                "help": "投注方案：和值3；开奖号码中三位：(1)开出003号码，顺序不限，即中中三组三；(2)开出012号码，顺序不限，即中中三组六。",
                "selectarea": {
                    "type": "digital",
                    "layout": [{
                        "balls": [1, 2, 3, 4, 5, 6, 7, 8, 9, 10, 11, 12, 13, 14, 15, 16, 17, 18, 19, 20, 21, 22, 23, 24, 25, 26],
                        "tools": false,
                        "cls": "hz"
                    }]
                }
            }]
        }]
    }, {
        "title": "前三",
        "rows": [{
            "title": "前三直选",
            "parentname": "qsanzx",
            "columns": [{
                "isrx": 0,
                "showname": "复式",
                "shortname": "sxzhixfsq",
                "parentname": "qsanzx",
                "realname": "[前三码_复式]",
                "tips": "从万、千、百位各选一个号码组成一注。",
                "example": "投注方案：345； 开奖号码：345，即中前三直选一等奖",
                "help": "从万位、千位、百位中选择一个3位数号码组成一注，所选号码与开奖号码的前3位相同，且顺序一致，即为中奖。",
                "selectarea": {
                    "type": "digital",
                    "layout": [{
                        "title": "万位",
                        "balls": [0, 1, 2, 3, 4, 5, 6, 7, 8, 9],
                        "tools": true
                    }, {
                        "title": "千位",
                        "balls": [0, 1, 2, 3, 4, 5, 6, 7, 8, 9],
                        "tools": true
                    }, {
                        "title": "百位",
                        "balls": [0, 1, 2, 3, 4, 5, 6, 7, 8, 9],
                        "tools": true
                    }]
                }
            }, {
                "isrx": 0,
                "showname": "单式",
                "parentname": "qsanzx",
                "shortname": "sxzhixdsq",
                "realname": "[前三码_单式]",
                "tips": "手动输入号码，至少输入1个三位数号码组成一注。",
                "example": "投注方案：345； 开奖号码：345，即中前三直选一等奖",
                "help": "手动输入一个3位数号码组成一注，所选号码的万位、千位、百位与开奖号码相同，且顺序一致，即为中奖。",
                "selectarea": {
                    "type": "input"
                }
            }, {
                "isrx": 0,
                "showname": "直选和值",
                "parentname": "qsanzx",
                "shortname": "sxzhixhzq",
                "realname": "[前三码_和值]",
                "tips": "从0-27中任意选择1个或1个以上号码",
                "example": "投注方案：和值1；开奖号码前三位：001,010,100,即中前三直选一等奖",
                "help": "所选数值等于开奖号码的万位、千位、百位三个数字相加之和，即为中奖。",
                "selectarea": {
                    "type": "digital",
                    "layout": [{
                        "balls": [0, 1, 2, 3, 4, 5, 6, 7, 8, 9, 10, 11, 12, 13, 14, 15, 16, 17, 18, 19, 20, 21, 22, 23, 24, 25, 26, 27],
                        "tools": false,
                        "cls": "hz"
                    }]
                }
            }]
        }, {
            "title": "前三组选",
            "parentname": "qsanzux",
            "columns": [{
                "isrx": 0,
                "showname": "组三",
                "parentname": "qsanzux",
                "shortname": "sxzuxzsq",
                "realname": "[前三码_组三]",
                "tips": "从0-9中任意选择2个或2个以上号码。",
                "example": "投注方案：5,8,8；开奖号码前三位：1个5，2个8 (顺序不限)，即中前三组选三一等奖。",
                "help": "从0-9中选择2个数字组成两注，所选号码与开奖号码的万位、千位、百位相同，且顺序不限，即为中奖。",
                "selectarea": {
                    "type": "digital",
                    "layout": [{
                        "title": "组三",
                        "balls": [0, 1, 2, 3, 4, 5, 6, 7, 8, 9],
                        "tools": true
                    }]
                }
            }, {
                "isrx": 0,
                "showname": "组六",
                "parentname": "qsanzux",
                "shortname": "sxzuxzlq",
                "realname": "[前三码_组六]",
                "tips": "从0-9中任意选择3个或3个以上号码。",
                "example": "投注方案：2,5,8；开奖号码前三位：1个2、1个5、1个8 (顺序不限)，即中前三组选六一等奖。",
                "help": "从0-9中任意选择3个号码组成一注，所选号码与开奖号码的万位、千位、百位相同，顺序不限，即为中奖。",
                "selectarea": {
                    "type": "digital",
                    "layout": [{
                        "title": "组六",
                        "balls": [0, 1, 2, 3, 4, 5, 6, 7, 8, 9],
                        "tools": true
                    }]
                }
            }, {
                "isrx": 0,
                "showname": "混合组选",
                "parentname": "qsanzux",
                "shortname": "sxhhzxq",
                "realname": "[前三码_混合组选]",
                "tips": "手动输入号码，至少输入1个三位数号码。",
                "example": "投注方案：分別投注(0,0,1),以及(1,2,3)，开奖号码前三位包括：(1)0,0,1，顺序不限，即中得组三一等奖；或者(2)1,2,3，顺序不限，即中得组六一等奖。",
                "help": "键盘手动输入购买号码，3个数字为一注，开奖号码的万位、千位、百位符合后三组三或组六均为中奖。",
                "selectarea": {
                    "type": "input"
                }
            },{
                "isrx": 0,
                "showname": "组选和值",
                "shortname": "sxzuxhzq",
                "parentname": "qsanzux",
                "realname": "[前三码_组选和值]",
                "tips": "从1-26中选择1个号码。",
                "example" : "所选数值等于开奖号码万位、千位、百位三个数字相加之和（豹子除外），即为中奖。",
                "help": "投注方案：和值3；开奖号码前三位：(1)开出003号码，顺序不限，即中前三组三；(2)开出012号码，顺序不限，即中前三组六。",
                "selectarea": {
                    "type": "digital",
                    "layout": [{
                        "balls": [1, 2, 3, 4, 5, 6, 7, 8, 9, 10, 11, 12, 13, 14, 15, 16, 17, 18, 19, 20, 21, 22, 23, 24, 25, 26],
                        "tools": false,
                        "cls": "hz"
                    }]
                }
            }]
        }]
    }, {
        "title": "前二星",
        "rows": [{
            "title": "前二星直选",
            "parentname": "qerzx",
            "columns": [{
                "isrx": 0,
                "showname": "复式",
                "shortname": "exzhixfsq",
                "parentname": "qerzx",
                "realname": "[直选复式]",
                "tips": "从万位、千位各选一个号码组成一注。",
                "example": "投注方案：5,8；开奖号码前二位：5,8；即中前二直选一等奖。",
                "help": "从万位、千位中选择一个2位数号码组成一注，所选号码与开奖号码的前2位相同，且顺序一致，即为中奖。",
                "selectarea": {
                    "type": "digital",
                    "layout": [{
                        "title": "万位",
                        "balls": [0, 1, 2, 3, 4, 5, 6, 7, 8, 9],
                        "tools": true
                    }, {
                        "title": "千位",
                        "balls": [0, 1, 2, 3, 4, 5, 6, 7, 8, 9],
                        "tools": true
                    }]
                }
            }, {
                "isrx": 0,
                "showname": "单式",
                "shortname": "exzhixdsq",
                "parentname": "qerzx",
                "realname": "[直选单式]",
                "tips": "手动输入号码，至少输入1个两位数号码。",
                "example": "投注方案：58；开奖号码前二位：58，即中前二直选一等奖。",
                "help": "手动输入一个2位数号码组成一注，所选号码的万位、千位与开奖号码相同，且顺序一致，即为中奖。",
                "selectarea": {
                    "type": "input"
                }
            }, {
                "isrx": 0,
                "showname": "直选和值",
                "shortname": "exzhixhzq",
                "realname": "[直选和值]",
                "parentname": "qerzx",
                "tips": "从0-18中任意选择1个或1个以上的和值号码。",
                "example": "投注方案：和值1；开奖号码前二位：01,10，即中前二直选和值。",
                "help": "所选数值等于开奖号码的万位、千位二个数字相加之和，即为中奖。",
                "selectarea": {
                    "type": "digital",
                    "layout": [{
                        "balls": [0, 1, 2, 3, 4, 5, 6, 7, 8, 9, 10, 11, 12, 13, 14, 15, 16, 17, 18],
                        "tools": false,
                        "cls": "hz"
                    }]
                }
            }, {
                "isrx": 0,
                "showname": "大小单双",
                "parentname": "qerzx",
                "shortname": "dxdsq",
                "realname": "[大小单双]",
                "tips": "从万位、千位中的“大、小、单、双”中至少各选一个组成一注。",
                "example": "投注方案：小双；开奖号码万位与千位：小双，即中前二大小单双一等奖。",
                "help": "对万位和千位的“大（56789）小（01234）、单（13579）双（02468）”形态进行购买，所选号码的位置、形态与开奖号码的位置、形态相同，即为中奖。",
                "selectarea": {
                    "type": "dxds",
                    "layout": [{
                        "title": "万位",
                        "balls": ["大", "小", "单", "双"],
                        "tools": false
                    }, {
                        "title": "千位",
                        "balls": ["大", "小", "单", "双"],
                        "tools": false
                    }]
                }
            }]
        }, {
            "title": "前二星组选",
            "parentname": "qerzux",
            "columns": [{
                "isrx": 0,
                "showname": "复式",
                "shortname": "exzuxfsq",
                "parentname": "qerzux",
                "realname": "[组选复式]",
                "tips": "从0-9中任意选择2个或2个以上号码。",
                "example": "投注方案：5,8；开奖号码前二位：1个5，1个8 (顺序不限)，即中前二组选一等奖。",
                "help": "从0-9中选2个号码组成一注，所选号码与开奖号码的万位、千位相同，顺序不限，即中奖。",
                "selectarea": {
                    "type": "digital",
                    "layout": [{
                        "title": "组选",
                        "balls": [0, 1, 2, 3, 4, 5, 6, 7, 8, 9],
                        "tools": true
                    }]
                }
            }, {
                "isrx": 0,
                "showname": "单式",
                "shortname": "exzuxdsq",
                "parentname": "qerzux",
                "realname": "[组选单式]",
                "tips": "手动输入号码，至少输入1个两位数号码。",
                "example": "投注方案：5,8；开奖号码后前位：1个5，1个8 (顺序不限)，即中前二组选一等奖。",
                "help": "手动输入一个2位数号码组成一注，所选号码的万位、千位与开奖号码相同，顺序不限，即为中奖。",
                "selectarea": {
                    "type": "input"
                }
            }, {
                "isrx": 0,
                "showname": "组选和值",
                "shortname": "exzuxhzq",
                "realname": "[组选和值]",
                "parentname": "qerzux",
                "tips": "从1-17中任意选择1个或1个以上的和值号码。",
                "example": "投注方案：和值3；开奖号码前二位：12,30，即中前二直选和值。",
                "help": "所选数值等于开奖号码的万位、千位二个数字相加之和（对子除外），即为中奖。",
                "selectarea": {
                    "type": "digital",
                    "layout": [{
                        "balls": [1, 2, 3, 4, 5, 6, 7, 8, 9, 10, 11, 12, 13, 14, 15, 16, 17],
                        "tools": false,
                        "cls": "hz"
                    }]
                }
            }]
        }]
    }, {
        "title": "后二星",
        "rows": [{
            "title": "后二星直选",
            "parentname": "herzx",
            "columns": [{
                "isrx": 0,
                "showname": "复式",
                "shortname": "exzhixfsh",
                "parentname": "herzx",
                "realname": "[直选复式]",
                "tips": "从十、个位各选一个号码组成一注。",
                "example": "投注方案：58；开奖号码后二位：58，即中后二直选一等奖。",
                "help": "从十位、个位中选择一个2位数号码组成一注，所选号码与开奖号码的十位、个位相同，且顺序一致，即为中奖。",
                "selectarea": {
                    "type": "digital",
                    "layout": [{
                        "title": "十位",
                        "balls": [0, 1, 2, 3, 4, 5, 6, 7, 8, 9],
                        "tools": true
                    }, {
                        "title": "个位",
                        "balls": [0, 1, 2, 3, 4, 5, 6, 7, 8, 9],
                        "tools": true
                    }]
                }
            }, {
                "isrx": 0,
                "showname": "单式",
                "shortname": "exzhixdsh",
                "parentname": "herzx",
                "realname": "[直选单式]",
                "tips": "手动输入号码，至少输入1个两位数号码。",
                "example": "投注方案：58；开奖号码后二位：58，即中后二直选一等奖。",
                "help": "手动输入一个2位数号码组成一注，所选号码的十位、个位与开奖号码相同，且顺序一致，即为中奖。",
                "selectarea": {
                    "type": "input"
                }
            }, {
                "isrx": 0,
                "showname": "直选和值",
                "shortname": "exzhixhzh",
                "parentname": "herzx",
                "realname": "[直选和值]",
                "tips": "从0-18中任意选择1个或1个以上的和值号码。",
                "example": "投注方案：和值1；开奖号码后二位：01,10，即中后二直选。",
                "help": "所选数值等于开奖号码的十位、个位二个数字相加之和，即为中奖。",
                "selectarea": {
                    "type": "digital",
                    "layout": [{
                        "balls": [0, 1, 2, 3, 4, 5, 6, 7, 8, 9, 10, 11, 12, 13, 14, 15, 16, 17, 18],
                        "tools": false,
                        "cls": "hz"
                    }]
                }
            }, {
                "isrx": 0,
                "showname": "大小单双",
                "shortname": "dxdsh",
                "parentname": "herzx",
                "realname": "[大小单双]",
                "tips": "从十位、个位中的“大、小、单、双”中至少各选一个组成一注。",
                "example": "投注方案：大单；开奖号码十位与个位：大单，即中后二大小单双一等奖。",
                "help": "对十位和个位的“大（56789）小（01234）、单（13579）双（02468）”形态进行购买，所选号码的位置、形态与开奖号码的位置、形态相同，即为中奖。",
                "selectarea": {
                    "type": "digital",
                    "layout": [{
                        "title": "十位",
                        "balls": ["大", "小", "单", "双"],
                        "tools": false
                    }, {
                        "title": "个位",
                        "balls": ["大", "小", "单", "双"],
                        "tools": false
                    }]
                }
            }]
        }, {
            "title": "后二星组选",
            "parentname": "herzux",
            "columns": [{
                "isrx": 0,
                "showname": "复式",
                "shortname": "exzuxfsh",
                "parentname": "herzux",
                "realname": "[组选复式]",
                "tips": "从0-9中任意选择2个或2个以上号码。",
                "example": "投注方案：5,8；开奖号码后二位：1个5，1个8 (顺序不限)，即中后二组选一等奖。",
                "help": "从0-9中选2个号码组成一注，所选号码与开奖号码的十位、个位相同，顺序不限，即中奖。",
                "selectarea": {
                    "type": "digital",
                    "layout": [{
                        "title": "组选",
                        "balls": [0, 1, 2, 3, 4, 5, 6, 7, 8, 9],
                        "tools": true
                    }]
                }
            }, {
                "isrx": 0,
                "showname": "单式",
                "shortname": "exzuxdsh",
                "realname": "[组选单式]",
                "parentname": "herzux",
                "tips": "手动输入号码，至少输入1个两位数号码。",
                "example": "投注方案：5,8；开奖号码后二位：1个5，1个8 (顺序不限)，即中后二组选一等奖。",
                "help": "手动输入一个2位数号码组成一注，所选号码的十位、个位与开奖号码相同，顺序不限，即为中奖。",
                "selectarea": {
                    "type": "input"
                }
            },{
                "isrx": 0,
                "showname": "组选和值",
                "shortname": "exzuxhzh",
                "realname": "[组选和值]",
                "parentname": "herzux",
                "tips": "从1-17中任意选择1个或1个以上的和值号码。",
                "example": "投注方案：和值3；开奖号码后二位：12,30，即中后二直选和值。",
                "help": "所选数值等于开奖号码的十位、个位二个数字相加之和（对子除外），即为中奖。",
                "selectarea": {
                    "type": "digital",
                    "layout": [{
                        "balls": [1, 2, 3, 4, 5, 6, 7, 8, 9, 10, 11, 12, 13, 14, 15, 16, 17],
                        "tools": false,
                        "cls": "hz"
                    }]
                }
            }]
        }]
    }, {
        "title": "定位胆",
        "rows": [{
            "title": "定位胆",
            "parentname": "dwd",
	    "default": "1",
	    "defaultmethod": "dw",
            "columns": [{
                "isrx": 0,
                "showname": "定位胆",
                "shortname": "dw",
                "realname": "定位胆",
                "parentname": "dwd",
                "tips": "在万千百十个位任意位置上任意选择1个或1个以上号码。",
                "example": "投注方案：1；开奖号码万位：1，即中定位胆万位一等奖。",
                "help": "从万位、千位、百位、十位、个位任意位置上至少选择1个以上号码，所选号码与相同位置上的开奖号码一致，即为中奖。",
                "selectarea": {
                    "type": "digital",
                    "layout": [{
                        "title": "万位",
                        "balls": [0, 1, 2, 3, 4, 5, 6, 7, 8, 9],
                        "tools": true
                    }, {
                        "title": "千位",
                        "balls": [0, 1, 2, 3, 4, 5, 6, 7, 8, 9],
                        "tools": true
                    }, {
                        "title": "百位",
                        "balls": [0, 1, 2, 3, 4, 5, 6, 7, 8, 9],
                        "tools": true
                    }, {
                        "title": "十位",
                        "balls": [0, 1, 2, 3, 4, 5, 6, 7, 8, 9],
                        "tools": true
                    }, {
                        "title": "个位",
                        "balls": [0, 1, 2, 3, 4, 5, 6, 7, 8, 9],
                        "tools": true
                    }]
                }
            }]
        }]
    }, {
        "title": "不定胆",
        "rows": [{
            "title": "三星不定胆",
            "parentname": "ymbdw",
            "columns": [{
                "isrx": 0,
                "showname": "后三一码",
                "shortname": "bdw1mh",
                "parentname": "ymbdw",
                "realname": "[不定胆_后三一码]",
                "tips": "从0-9中任意选择1个以上号码。",
                "example": "投注方案：1；开奖号码后三位：至少出现1个1，即中后三一码不定位一等奖。",
                "help": "从0-9中选择1个号码，每注由1个号码组成，只要开奖号码的百位、十位、个位中包含所选号码，即为中奖。",
                "selectarea": {
                    "type": "digital",
                    "layout": [{
                        "title": "不定胆",
                        "balls": [0, 1, 2, 3, 4, 5, 6, 7, 8, 9],
                        "tools": true
                    }]
                }
            }, {
                "isrx": 0,
                "showname": "中三一码",
                "parentname": "ymbdw",
                "shortname": "bdw1mz",
                "realname": "[不定胆_中三一码]",
                "tips": "投注方案：1；开奖号码中间三位：至少出现1个1，即中中三一码不定位一等奖。",
                "example": "从0-9中选择1个号码，每注由1个号码组成，只要开奖号码的千位、百位、十位中包含所选号码，即为中奖。",
                "help": "帮助",
                "selectarea": {
                    "type": "digital",
                    "layout": [{
                        "title": "不定胆",
                        "balls": [0, 1, 2, 3, 4, 5, 6, 7, 8, 9],
                        "tools": true
                    }]
                }
            }, {
                "isrx": 0,
                "showname": "前三一码",
                "parentname": "ymbdw",
                "shortname": "bdw1mq",
                "realname": "[不定胆_前三一码]",
                "tips": "从0-9中任意选择1个以上号码。",
                "example": "投注方案：1；开奖号码前三位：至少出现1个1，即中前三一码不定位一等奖。",
                "help": "从0-9中选择1个号码，每注由1个号码组成，只要开奖号码的万位、千位、百位中包含所选号码，即为中奖。",
                "selectarea": {
                    "type": "digital",
                    "layout": [{
                        "title": "不定胆",
                        "balls": [0, 1, 2, 3, 4, 5, 6, 7, 8, 9],
                        "tools": true
                    }]
                }
            }]
        }, {
            "title": "三星不定胆",
            "parentname": "embdw",
            "columns": [{
                "isrx": 0,
                "showname": "后三二码",
                "shortname": "bdw2mh",
                "parentname": "embdw",
                "realname": "[不定胆_后三二码]",
                "tips": "从0-9中任意选择2个以上号码。",
                "example": "投注方案：1,2；开奖号码后三位：至少出现1和2各1个，即中后三二码不定位一等奖。",
                "help": "从0-9中选择2个号码，每注由2个不同的号码组成，开奖号码的百位、十位、个位中同时包含所选的2个号码，即为中奖。",
                "selectarea": {
                    "type": "digital",
                    "layout": [{
                        "title": "不定胆",
                        "balls": [0, 1, 2, 3, 4, 5, 6, 7, 8, 9],
                        "tools": true
                    }]
                }
            }, {
                "isrx": 0,
                "showname": "中三二码",
                "shortname": "bdw2mz",
                "realname": "[不定胆_中三二码]",
                "parentname": "embdw",
                "tips": "从0-9中任意选择2个以上号码。",
                "example": "投注方案：1,2；开奖号码中间三位：至少出现1和2各1个，即中中三二码不定位一等奖。",
                "help": "从0-9中选择2个号码，每注由2个不同的号码组成，开奖号码的千位、百位、十位中同时包含所选的2个号码，即为中奖。",
                "selectarea": {
                    "type": "digital",
                    "layout": [{
                        "title": "不定胆",
                        "balls": [0, 1, 2, 3, 4, 5, 6, 7, 8, 9],
                        "tools": true
                    }]
                }
            }, {
                "isrx": 0,
                "showname": "前三二码",
                "shortname": "bdw2mq",
                "realname": "[不定胆_前三二码]",
                "parentname": "embdw",
                "tips": "从0-9中任意选择2个以上号码。",
                "example": "投注方案：1,2；开奖号码前三位：至少出现1和2各1个，即中前三二码不定位一等奖。",
                "help": "从0-9中选择2个号码，每注由2个不同的号码组成，开奖号码的万位、千位、百位中同时包含所选的2个号码，即为中奖。",
                "selectarea": {
                    "type": "digital",
                    "layout": [{
                        "title": "不定胆",
                        "balls": [0, 1, 2, 3, 4, 5, 6, 7, 8, 9],
                        "tools": true
                    }]
                }
            }]
        }, {
            "title": "四星不定胆",
            "parentname": "sixymbdw",
            "columns": [{
                "isrx": 0,
                "showname": "后四一码",
                "shortname": "bdwsix1mh",
                "parentname": "sixymbdw",
                "realname": "[不定胆_后四一码]",
                "tips": "从0-9中任意选择1个以上号码。",
                "example": "投注方案：1；开奖号码后四位：至少出现1个1，即中后四一码不定位一等奖。",
                "help": "从0-9中选择1个号码，每注由1个号码组成，只要开奖号码的千位、百位、十位、个位中包含所选号码，即为中奖。",
                "selectarea": {
                    "type": "digital",
                    "layout": [{
                        "title": "不定胆",
                        "balls": [0, 1, 2, 3, 4, 5, 6, 7, 8, 9],
                        "tools": true
                    }]
                }
            }, {
                "isrx": 0,
                "showname": "前四一码",
                "parentname": "sixymbdw",
                "shortname": "bdwsix1mq",
                "realname": "[不定胆_前四一码]",
                "tips": "投注方案：1；开奖号码前四位：至少出现1个1，即中前四一码不定位一等奖。",
                "example": "从0-9中选择1个号码，每注由1个号码组成，只要开奖号码的万位、千位、百位、十位中包含所选号码，即为中奖。",
                "help": "帮助",
                "selectarea": {
                    "type": "digital",
                    "layout": [{
                        "title": "不定胆",
                        "balls": [0, 1, 2, 3, 4, 5, 6, 7, 8, 9],
                        "tools": true
                    }]
                }
            }]
        }, {
            "title": "四星不定胆",
            "parentname": "sixembdw",
            "columns": [{
                "isrx": 0,
                "showname": "后四二码",
                "shortname": "bdwsix2mh",
                "parentname": "sixembdw",
                "realname": "[不定胆_后四二码]",
                "tips": "从0-9中任意选择2个以上号码。",
                "example": "投注方案：1,2；开奖号码后四位：至少出现1和2各1个，即中后四二码不定位一等奖。",
                "help": "从0-9中选择2个号码，每注由2个不同的号码组成，开奖号码的千位、百位、十位、个位中同时包含所选的2个号码，即为中奖。",
                "selectarea": {
                    "type": "digital",
                    "layout": [{
                        "title": "不定胆",
                        "balls": [0, 1, 2, 3, 4, 5, 6, 7, 8, 9],
                        "tools": true
                    }]
                }
            }, {
                "isrx": 0,
                "showname": "前四二码",
                "shortname": "bdwsix2mq",
                "realname": "[不定胆_前四二码]",
                "parentname": "sixembdw",
                "tips": "从0-9中任意选择2个以上号码。",
                "example": "投注方案：1,2；开奖号码前四位：至少出现1和2各1个，即中前四二码不定位一等奖。",
                "help": "从0-9中选择2个号码，每注由2个不同的号码组成，开奖号码的万位、千位、百位、十位中同时包含所选的2个号码，即为中奖。",
                "selectarea": {
                    "type": "digital",
                    "layout": [{
                        "title": "不定胆",
                        "balls": [0, 1, 2, 3, 4, 5, 6, 7, 8, 9],
                        "tools": true
                    }]
                }
            }]
        }, {
            "title": "五星不定胆",
            "parentname": "wuxembdw",
            "columns": [{
                "isrx": 0,
                "showname": "二码",
                "shortname": "bdwwx2m",
                "parentname": "wuxembdw",
                "realname": "[不定胆_五星二码]",
                "tips": "从0-9中任意选择2个以上号码。",
                "example": "投注方案：1,2；开奖号码中至少出现1和2各1个，即中五星二码不定位一等奖。",
                "help": "从0-9中选择2个号码，每注由2个不同的号码组成，开奖号码的万位、千位、百位、十位、个位中同时包含所选的2个号码，即为中奖。",
                "selectarea": {
                    "type": "digital",
                    "layout": [{
                        "title": "不定胆",
                        "balls": [0, 1, 2, 3, 4, 5, 6, 7, 8, 9],
                        "tools": true
                    }]
                }
            }, {
                "isrx": 0,
                "showname": "三码",
                "shortname": "bdwwx3m",
                "realname": "[不定胆_五星三码]",
                "parentname": "wuxembdw",
                "tips": "从0-9中任意选择3个以上号码。",
                "example": "投注方案：1,2,3；开奖号码中至少出现1和2和3各1个，即中五星三码不定位一等奖。",
                "help": "从0-9中选择3个号码，每注由3个不同的号码组成，开奖号码的万位、千位、百位、十位、个位中同时包含所选的3个号码，即为中奖。",
                "selectarea": {
                    "type": "digital",
                    "layout": [{
                        "title": "不定胆",
                        "balls": [0, 1, 2, 3, 4, 5, 6, 7, 8, 9],
                        "tools": true
                    }]
                }
            }]
        }]
    }, {
        "title": "任选",
        "rows": [{
            "title": "直选复试",
            "parentname": "rxzx",
            "columns": [{
                "isrx": "1",
                "showname": "任二",
                "shortname": "rx2fs",
                "parentname": "rxzx",
                "realname": "[任选二_复试]",
                "tips": "万、千、百、十、个任意2位，开奖号分别对应且顺序一致即中奖",
                "example": "投注方案：万位1，百位2；开奖号码：13245， 即中任选二直选一等奖。",
                "help": "从万、千、百、十、个中至少2个位置各选一个或多个号码，将各个位置的号码进行组合，所选号码的各位与开奖号码相同则中奖。",
                "selectarea": {
                    "type": "digital",
                    "layout": [{
                        "title": "万位",
                        "balls": [0, 1, 2, 3, 4, 5, 6, 7, 8, 9],
                        "tools": true
                    }, {
                        "title": "千位",
                        "balls": [0, 1, 2, 3, 4, 5, 6, 7, 8, 9],
                        "tools": true
                    }, {
                        "title": "百位",
                        "balls": [0, 1, 2, 3, 4, 5, 6, 7, 8, 9],
                        "tools": true
                    }, {
                        "title": "十位",
                        "balls": [0, 1, 2, 3, 4, 5, 6, 7, 8, 9],
                        "tools": true
                    }, {
                        "title": "个位",
                        "balls": [0, 1, 2, 3, 4, 5, 6, 7, 8, 9],
                        "tools": true
                    }]
                }
            }, {
                "isrx": "1",
                "showname": "任三",
                "shortname": "rx3fs",
                "realname": "[任选三_复试]",
                "parentname": "rxzx",
                "tips": "万、千、百、十、个任意3位，开奖号分别对应且顺序一致即中奖",
                "example": "万位买0，千位买1，百万买2，十位买3，开奖01234，则中奖。",
                "help": "从万位、千位、百位、十位、个位中至少三位上各选1个号码组成一注，所选号码与开奖号码的指定位置上的号码相同，且顺序一致，即为中奖。",
                "selectarea": {
                    "type": "digital",
                    "layout": [{
                        "title": "万位",
                        "balls": [0, 1, 2, 3, 4, 5, 6, 7, 8, 9],
                        "tools": true
                    }, {
                        "title": "千位",
                        "balls": [0, 1, 2, 3, 4, 5, 6, 7, 8, 9],
                        "tools": true
                    }, {
                        "title": "百位",
                        "balls": [0, 1, 2, 3, 4, 5, 6, 7, 8, 9],
                        "tools": true
                    }, {
                        "title": "十位",
                        "balls": [0, 1, 2, 3, 4, 5, 6, 7, 8, 9],
                        "tools": true
                    }, {
                        "title": "个位",
                        "balls": [0, 1, 2, 3, 4, 5, 6, 7, 8, 9],
                        "tools": true
                    }]
                }
            }, {
                "isrx": "1",
                "showname": "任四",
                "shortname": "rx4fs",
                "realname": "[任选四_复试]",
                "parentname": "rxzx",
                "tips": "万、千、百、十、个任意4位，开奖号分别对应且顺序一致即中奖",
                "example": "投注方案：万位买0，千位买1，百万买2，十位买3，个位买4，开奖01234，则中奖。",
                "help": "从万、千、百、十、个中至少4个位置各选一个或多个号码，将各个位置的号码进行组合，所选号码的各位与开奖号码相同则中奖。",
                "selectarea": {
                    "type": "digital",
                    "layout": [{
                        "title": "万位",
                        "balls": [0, 1, 2, 3, 4, 5, 6, 7, 8, 9],
                        "tools": true
                    }, {
                        "title": "千位",
                        "balls": [0, 1, 2, 3, 4, 5, 6, 7, 8, 9],
                        "tools": true
                    }, {
                        "title": "百位",
                        "balls": [0, 1, 2, 3, 4, 5, 6, 7, 8, 9],
                        "tools": true
                    }, {
                        "title": "十位",
                        "balls": [0, 1, 2, 3, 4, 5, 6, 7, 8, 9],
                        "tools": true
                    }, {
                        "title": "个位",
                        "balls": [0, 1, 2, 3, 4, 5, 6, 7, 8, 9],
                        "tools": true
                    }]
                }
            }]
        }, {
            "title": "直选单式",
            "parentname": "rxds",
            "columns": [{
                "isrx": "1",
                "showname": "任二",
                "shortname": "rx2ds",
                "realname": "[任选二_单式]",
                "defaultposition": "00011",
                "parentname": "rxds",
                "tips": "手动输入号码，至少输入1个两位数号码和至少选择两个位置",
                "example": "投注方案：输入号码01并选择万、千位置位，如开奖号码位01***； 则中奖。",
                "help": "手动输入一注或者多注的两个号码和至少两个位置，如果选中的号码与位置和开奖号码对应则中奖。",
                "checkbox": {
                    "layout": [{
                        "title": "位置",
                        "value": ["万位", "千位", "百位", "十位", "个位"]
                    }]
                },
                "selectarea": {
                    "type": "input"
                }
            }, {
                "isrx": "1",
                "showname": "任三",
                "shortname": "rx3ds",
                "parentname": "rxds",
                "realname": "[任选三_单式]",
                "defaultposition": "00111",
                "tips": "手动输入号码，至少输入1个三位数号码和至少选择三个位置",
                "example": "投注方案：输入号码012选择万、千、百位置，如开奖号码位012**； 则中奖.",
                "help": "手动输入一注或者多注的三个号码和至少三个位置，如果选中的号码与位置和开奖号码对应则中奖。",
                "checkbox": {
                    "layout": [{
                        "title": "位置",
                        "value": ["万位", "千位", "百位", "十位", "个位"]
                    }]
                },
                "selectarea": {
                    "type": "input"
                }
            }, {
                "isrx": "1",
                "showname": "任四",
                "shortname": "rx4ds",
                "realname": "[任选四_单式]",
                "defaultposition": "01111",
                "parentname": "rxds",
                "tips": "手动输入号码，至少输入1个四位数号码和至少选择四个位置",
                "example": "投注方案：输入号码0123选择万、千、百、十位置，如开奖号码位0123*； 则中奖。",
                "help": "手动输入一注或者多注的四个号码和至少四个位置，如果选中的号码与位置和开奖号码对应则中奖。",
                "checkbox": {
                    "layout": [{
                        "title": "位置",
                        "value": ["万位", "千位", "百位", "十位", "个位"]
                    }]
                },
                "selectarea": {
                    "type": "input"
                }
            }]
        }, {
            "title": "任选组选",
            "parentname": "rxzux",
            "columns": [{
                "isrx": "1",
                "showname": "任三组三",
                "shortname": "rx3z3",
                "parentname": "rxzux",
                "realname": "[任选三_组三]",
                "defaultposition": "00111",
                "tips": "从0-9中任意选择2个或2个以上号码和任意三个位置",
                "example": "投注方案：位置选择万、千、百，号码选择01；开奖号码为110**、则中奖。",
                "help": "从0-9中任意选择2个或2个以上号码和万、千、百、十、个任意的三个位置，如何组合的号码与开奖号码对应则中奖。",
                "checkbox": {
                    "layout": [{
                        "title": "位置",
                        "value": ["万位", "千位", "百位", "十位", "个位"]
                    }]
                },
                "selectarea": {
                    "type": "digital",
                    "layout": [{
                        "title": "号码",
                        "balls": [0, 1, 2, 3, 4, 5, 6, 7, 8, 9],
                        "tools": true
                    }]
                }
            }, {
                "isrx": "1",
                "showname": "任三组六",
                "parentname": "rxzux",
                "shortname": "rx3z6",
                "realname": "[任选三_组六]",
                "defaultposition": "00111",
                "tips": "从0-9中任意选择3个或3个以上号码和任意三个位置",
                "example": "投注方案：位置选择万、千、百，号码选择012；开奖号码为012**、则中奖。",
                "help": "从0-9中任意选择3个或3个以上号码和万、千、百、十、个任意的三个位置，如何组合的号码与开奖号码对应则中奖。",
                "checkbox": {
                    "layout": [{
                        "title": "位置",
                        "value": ["万位", "千位", "百位", "十位", "个位"]
                    }]
                },
                "selectarea": {
                    "type": "digital",
                    "layout": [{
                        "title": "号码",
                        "balls": [0, 1, 2, 3, 4, 5, 6, 7, 8, 9],
                        "tools": true
                    }]
                }
            }, {
                "isrx": "1",
                "showname": "任三混合组选",
                "parentname": "rxzux",
                "shortname": "rx3hhzx",
                "defaultposition": "00111",
                "realname": "[任选三_混合组选]",
                "tips": "手动输入号码，至少输入1个三位数号码和至少选择三个位置",
                "example": "投注方案：位置选择万、千、百，号码输入001以及123，开奖号码万千百位包括：(1)0,0,1，顺序不限，即中得组三一等奖；或者(2)1,2,3，顺序不限，即中得组六一等奖。",
                "help": "任意选择3个以上位置，并动输入购买号码，3个数字为一注，所选位置与开奖号码相同并符合组三或组六均为中奖。",
                "checkbox": {
                    "layout": [{
                        "title": "位置",
                        "value": ["万位", "千位", "百位", "十位", "个位"]
                    }]
                },
                "selectarea": {
                    "type": "input"
                }
            }, {
                "isrx": "1",
                "showname": "任二组选",
                "parentname": "rxzux",
                "shortname": "rx2zx",
                "realname": "[任选二_组选]",
                "defaultposition": "00011",
                "tips": "从0-9中任意选择2个或2个以上号码和任意两个位置",
                "example": "投注方案：位置选择万、千，号码选择01；开奖号码为01***、则中奖。",
                "help": "从0-9中任意选择2个或2个以上号码和万、千、百、十、个任意的两个位置，如何组合的号码与开奖号码对应则中奖",
                "checkbox": {
                    "layout": [{
                        "title": "位置",
                        "value": ["万位", "千位", "百位", "十位", "个位"]
                    }]
                },
                "selectarea": {
                    "type": "digital",
                    "layout": [{
                        "title": "号码",
                        "balls": [0, 1, 2, 3, 4, 5, 6, 7, 8, 9],
                        "tools": true
                    }]
                }
            }]
        }]
    }, {
        "title": "趣味",
        "rows": [{
            "title": "特殊",
            "parentname": "quwei",
            "columns": [{
                "isrx": 0,
                "showname": "一帆风顺",
                "shortname": "qwyffs",
                "parentname": "quwei",
                "realname": "[特殊_一帆风顺]",
                "tips": "从0-9中任意选择1个以上号码。",
                "example": "投注方案：8；开奖号码：至少出现1个8，即中一帆风顺。",
                "help": "从0-9中任意选择1个号码组成一注，只要开奖号码的万位、千位、百位、十位、个位中包含所选号码，即为中奖。",
                "selectarea": {
                    "type": "digital",
                    "layout": [{
                        "title": "选号",
                        "balls": [0, 1, 2, 3, 4, 5, 6, 7, 8, 9],
                        "tools": true
                    }]
                }
            }, {
                "isrx": 0,
                "showname": "好事成双",
                "shortname": "qwhscs",
                "realname": "[特殊_好事成双]",
                "tips": "从0-9中任意选择1个以上的二重号码。",
                "example": "投注方案：8；开奖号码：至少出现2个8，即中好事成双。",
                "help": "从0-9中任意选择1个号码组成一注，只要所选号码在开奖号码的万位、千位、百位、十位、个位中出现2次，即为中奖。",
                "selectarea": {
                    "type": "digital",
                    "layout": [{
                        "title": "选号",
                        "balls": [0, 1, 2, 3, 4, 5, 6, 7, 8, 9],
                        "tools": true
                    }]
                }
            }, {
                "isrx": 0,
                "showname": "三星报喜",
                "shortname": "qwsxbx",
                "realname": "[特殊_三星报喜]",
                "tips": "从0-9中任意选择1个以上的三重号码。",
                "example": "投注方案：8；开奖号码：至少出现3个8，即中三星报喜。",
                "help": "从0-9中任意选择1个号码组成一注，只要所选号码在开奖号码的万位、千位、百位、十位、个位中出现3次，即为中奖。",
                "selectarea": {
                    "type": "digital",
                    "layout": [{
                        "title": "选号",
                        "balls": [0, 1, 2, 3, 4, 5, 6, 7, 8, 9],
                        "tools": true
                    }]
                }
            }, {
                "isrx": 0,
                "showname": "四季发财",
                "shortname": "qwsjfc",
                "realname": "[特殊_四季发财]",
                "tips": "从0-9中任意选择1个以上的四重号码。",
                "example": "投注方案：8；开奖号码：至少出现4个8，即中四季发财。",
                "help": "从0-9中任意选择1个号码组成一注，只要所选号码在开奖号码的万位、千位、百位、十位、个位中出现4次，即为中奖。",
                "selectarea": {
                    "type": "digital",
                    "layout": [{
                        "title": "选号",
                        "balls": [0, 1, 2, 3, 4, 5, 6, 7, 8, 9],
                        "tools": true
                    }]
                }
            }]
        }]
    }, {
        "title": "龙虎和",
        "rows": [{
            "title": "龙虎和",
            "parentname": "longhuhe",
            "columns": [{
                "isrx": 0,
                "showname": "万千",
                "shortname": "longhuhewq",
                "parentname": "longhuhe",
                "realname": "[龙虎和_万千]",
                "tips": "选择龙或虎或和。",
                "example": "选择龙或虎或和。",
                "help": "在龙、虎、和三种形态中选择一种。用开奖号码的万位、千位数字比较大小，万位大于千位为龙；万位小于千位为虎；万位等于千位为和。开奖结果与投注项相符，即为中奖。",
                "selectarea": {
                    "type": "digital",
                    "layout": [{
                        "title": "万千",
                        "balls": ["龙", "虎", "和"],
                        "tools": false
                    }]
                }
            }, {
                "isrx": 0,
                "showname": "万百",
                "shortname": "longhuhewb",
                "parentname": "longhuhe",
                "realname": "[龙虎和_万百]",
                "tips": "选择龙或虎或和。",
                "example": "选择龙或虎或和。",
                "help": "在龙、虎、和三种形态中选择一种。用开奖号码的万位、千位数字比较大小，万位大于千位为龙；万位小于千位为虎；万位等于千位为和。开奖结果与投注项相符，即为中奖。",
                "selectarea": {
                    "type": "digital",
                    "layout": [{
                        "title": "万百",
                        "balls": ["龙", "虎", "和"],
                        "tools": false
                    }]
                }
            }, {
                "isrx": 0,
                "showname": "万十",
                "shortname": "longhuhews",
                "parentname": "longhuhe",
                "realname": "[龙虎和_万十]",
                "tips": "选择龙或虎或和。",
                "example": "选择龙或虎或和。",
                "help": "在龙、虎、和三种形态中选择一种。用开奖号码的万位、千位数字比较大小，万位大于千位为龙；万位小于千位为虎；万位等于千位为和。开奖结果与投注项相符，即为中奖。",
                "selectarea": {
                    "type": "digital",
                    "layout": [{
                        "title": "万十",
                        "balls": ["龙", "虎", "和"],
                        "tools": false
                    }]
                }
            }, {
                "isrx": 0,
                "showname": "万个",
                "shortname": "longhuhewg",
                "parentname": "longhuhe",
                "realname": "[龙虎和_万个]",
                "tips": "选择龙或虎或和。",
                "example": "选择龙或虎或和。",
                "help": "在龙、虎、和三种形态中选择一种。用开奖号码的万位、千位数字比较大小，万位大于千位为龙；万位小于千位为虎；万位等于千位为和。开奖结果与投注项相符，即为中奖。",
                "selectarea": {
                    "type": "digital",
                    "layout": [{
                        "title": "万个",
                        "balls": ["龙", "虎", "和"],
                        "tools": false
                    }]
                }
            }, {
                "isrx": 0,
                "showname": "千百",
                "shortname": "longhuheqb",
                "parentname": "longhuhe",
                "realname": "[龙虎和_千百]",
                "tips": "选择龙或虎或和。",
                "example": "选择龙或虎或和。",
                "help": "在龙、虎、和三种形态中选择一种。用开奖号码的万位、千位数字比较大小，万位大于千位为龙；万位小于千位为虎；万位等于千位为和。开奖结果与投注项相符，即为中奖。",
                "selectarea": {
                    "type": "digital",
                    "layout": [{
                        "title": "千百",
                        "balls": ["龙", "虎", "和"],
                        "tools": false
                    }]
                }
            }, {
                "isrx": 0,
                "showname": "千十",
                "shortname": "longhuheqs",
                "parentname": "longhuhe",
                "realname": "[龙虎和_千十]",
                "tips": "选择龙或虎或和。",
                "example": "选择龙或虎或和。",
                "help": "在龙、虎、和三种形态中选择一种。用开奖号码的万位、千位数字比较大小，万位大于千位为龙；万位小于千位为虎；万位等于千位为和。开奖结果与投注项相符，即为中奖。",
                "selectarea": {
                    "type": "digital",
                    "layout": [{
                        "title": "千十",
                        "balls": ["龙", "虎", "和"],
                        "tools": false
                    }]
                }
            }, {
                "isrx": 0,
                "showname": "千个",
                "shortname": "longhuheqg",
                "realname": "[龙虎和_千个]",
                "tips": "选择龙或虎或和。",
                "parentname": "longhuhe",
                "example": "选择龙或虎或和。",
                "help": "在龙、虎、和三种形态中选择一种。用开奖号码的万位、千位数字比较大小，万位大于千位为龙；万位小于千位为虎；万位等于千位为和。开奖结果与投注项相符，即为中奖。",
                "selectarea": {
                    "type": "digital",
                    "layout": [{
                        "title": "千个",
                        "balls": ["龙", "虎", "和"],
                        "tools": false
                    }]
                }
            }, {
                "isrx": 0,
                "showname": "百十",
                "shortname": "longhuhebs",
                "realname": "[龙虎和_百十]",
                "parentname": "longhuhe",
                "tips": "选择龙或虎或和。",
                "example": "选择龙或虎或和。",
                "help": "在龙、虎、和三种形态中选择一种。用开奖号码的万位、千位数字比较大小，万位大于千位为龙；万位小于千位为虎；万位等于千位为和。开奖结果与投注项相符，即为中奖。",
                "selectarea": {
                    "type": "digital",
                    "layout": [{
                        "title": "百十",
                        "balls": ["龙", "虎", "和"],
                        "tools": false
                    }]
                }
            }, {
                "isrx": 0,
                "showname": "十个",
                "shortname": "longhuhesg",
                "realname": "[龙虎和_十个]",
                "parentname": "longhuhe",
                "tips": "选择龙或虎或和。",
                "example": "选择龙或虎或和。",
                "help": "在龙、虎、和三种形态中选择一种。用开奖号码的万位、千位数字比较大小，万位大于千位为龙；万位小于千位为虎；万位等于千位为和。开奖结果与投注项相符，即为中奖。",
                "selectarea": {
                    "type": "digital",
                    "layout": [{
                        "title": "十个",
                        "balls": ["龙", "虎", "和"],
                        "tools": false
                    }]
                }
            }]
        }]
    }, {
        "title": "牛牛",
        "rows": [{
            "title": "牛牛",
            "parentname": "niuniu",
            "columns": [{
                "isrx": 0,
                "showname": "牛牛",
                "shortname": "sscniuniu",
                "parentname": "niuniu",
                "realname": "[牛牛]",
                "tips": "任意选择一个号码形态组成一注。",
                "example": "牛1-牛9：开奖号码中任意三位数相加可以为0或10的倍数，另外两个数字相加的个位数为1-9，如：00026为牛8、02818为牛9； <br/><br/>牛牛：开奖号码中任意三位数相加可以为0或10的倍数，另外两个数字相加的个位数为0，如：68628、23500；<br/><br/>无牛：开奖号码中任意三位数相加都无法是0或10的倍数，如：37378、19197；<br/><br/>牛大：牛6、牛7、牛8、牛9、牛牛；<br/><br/>牛小：牛1、牛2、牛3、牛4、牛5；<br/><br/>牛单：牛1、牛3、牛5、牛7、牛9；<br/><br/>牛双：牛2、牛4、牛6、牛8、牛牛；<br/><br/>五条：开出五个号码中五个相同。如：00000/99999；<br/><br/>炸弹：开出五个号码中四个相同。如：10000/22221；<br/><br/>葫芦：开出五个号码中三个相同(三条)及两个号码相同(一对)。如：11222/33444；<br/><br/>顺子：开出五个号码从小到大排列为01234/ 12345/ 23456/ 34567/ 45678/ 56789/ 06789/ 01789/ 01289/01239；<br/><br/>三条：开出五个号码中三个相同(三条)及两个号码不相同。如：12333/66678；<br/><br/>两对：开出五个号码中有两组相同。如：00112/36677；<br/><br/>单对：开出五个号码中只有一组相同。如：00123/13556；<br/><br/>散号：开出五个号码没有任何相同或相关联。如：12356/01345/34678/12579；",
                "help": "所选号码符合以上规则、即为中奖。",
                "selectarea": {
                    "type": "digital",
                    "layout": [{
                        "title": "牛牛",
                        "balls": ["牛大","牛小", "牛单", "牛双", "无牛", "牛牛", "牛1", "牛2", "牛3", "牛4", "牛5", "牛6", "牛7", "牛8", "牛9", "五条", "炸弹", "葫芦", "顺子", "三条", "两对", "单对", "散号"],
                        "tools": false
                    }]
                }
            }]
        }]
    }]
}